hello/__init__.py
hello/cli.py
pravash-0.7.dist-info/LICENSE
pravash-0.7.dist-info/METADATA
pravash-0.7.dist-info/WHEEL
pravash-0.7.dist-info/entry_points.txt
pravash-0.7.dist-info/top_level.txt
pravash-0.7.dist-info/RECORD
