Metadata-Version: 2.1
Name: pravash
Version: 0.7
Summary: My first python package
Home-page: UNKNOWN
Author: Pravash Raj Upreti
Author-email: pravashupreti@gmail.com
License: MIT
Project-URL: Source, https://github.com/pravash-upreti/first-pip-package
Project-URL: Documentation, https://github.com/pravash-upreti/first-pip-package/blob/master/README.md
Keywords: cli
Platform: UNKNOWN
Classifier: Intended Audience :: Developers
Classifier: Topic :: Utilities
Classifier: License :: Public Domain
Classifier: Natural Language :: English
Classifier: Operating System :: OS Independent
Classifier: Programming Language :: Python :: 3.2
Classifier: Programming Language :: Python :: 3.3
Classifier: Programming Language :: Python :: 3.4
Requires-Dist: Click (==7.0)
